pysnirf2/__init__.py
pysnirf2/__version__.py
pysnirf2/pysnirf2.py
pysnirf2-0.7.3.dist-info/LICENSE
pysnirf2-0.7.3.dist-info/METADATA
pysnirf2-0.7.3.dist-info/WHEEL
pysnirf2-0.7.3.dist-info/top_level.txt
pysnirf2-0.7.3.dist-info/RECORD
