Metadata-Version: 2.1
Name: pysnirf2
Version: 0.7.3
Summary: Interface and validator for SNIRF files
Home-page: https://github.com/BUNPC/pysnirf2
Author-email: sstucker@bu.edu
License: GPLv3
Platform: UNKNOWN
Classifier: License :: OSI Approved :: MIT License
Classifier: Programming Language :: Python
Classifier: Programming Language :: Python :: 3
Classifier: Programming Language :: Python :: 3.6
Classifier: Programming Language :: Python :: Implementation :: CPython
Classifier: Programming Language :: Python :: Implementation :: PyPy
Requires-Python: >=3.6.0
Requires-Dist: h5py (>=3.1.0)
Requires-Dist: numpy
Requires-Dist: setuptools
Requires-Dist: pip
Requires-Dist: termcolor
Requires-Dist: colorama
